abstract_addresses/__init__.py
abstract_addresses/abstract_municipalities.py
abstract_addresses/add_addresses.py
abstract_addresses/addressDistributor.py
abstract_addresses/california_municipalities.py
abstract_addresses/check_db_cointents.py
abstract_addresses/db_utils.py
abstract_addresses/pre_parse.py
abstract_addresses/test_db (Copy).py
abstract_addresses/test_db.py
abstract_addresses/update_db.py
abstract_addresses-0.0.0.30.dist-info/METADATA
abstract_addresses-0.0.0.30.dist-info/WHEEL
abstract_addresses-0.0.0.30.dist-info/top_level.txt
abstract_addresses-0.0.0.30.dist-info/RECORD
